testrail_api_module/__init__.py
testrail_api_module/attachments.py
testrail_api_module/base.py
testrail_api_module/bdd.py
testrail_api_module/cases.py
testrail_api_module/configurations.py
testrail_api_module/datasets.py
testrail_api_module/groups.py
testrail_api_module/milestones.py
testrail_api_module/plans.py
testrail_api_module/priorities.py
testrail_api_module/projects.py
testrail_api_module/py.typed
testrail_api_module/reports.py
testrail_api_module/result_fields.py
testrail_api_module/results.py
testrail_api_module/roles.py
testrail_api_module/runs.py
testrail_api_module/sections.py
testrail_api_module/shared_steps.py
testrail_api_module/statuses.py
testrail_api_module/suites.py
testrail_api_module/templates.py
testrail_api_module/tests.py
testrail_api_module/users.py
testrail_api_module/variables.py
testrail_api_module-0.4.0.dist-info/licenses/LICENSE
testrail_api_module-0.4.0.dist-info/METADATA
testrail_api_module-0.4.0.dist-info/WHEEL
testrail_api_module-0.4.0.dist-info/top_level.txt
testrail_api_module-0.4.0.dist-info/RECORD
