Metadata-Version: 2.4
Name: testrail_api_module
Version: 0.4.0
Summary: A comprehensive Python wrapper for the TestRail API with enhanced error handling and performance improvements
Author-email: Matt Troutman <github@trtmn.com>, Christian Thompson <example@example.com>
License: MIT License
Project-URL: Homepage, https://github.com/trtmn/testrail_api_module
Project-URL: Docs, https://trtmn.github.io/testrail_api_module/
Requires-Python: >=3.11
License-File: LICENSE
Requires-Dist: requests>=2.32.0
Provides-Extra: dev
Requires-Dist: pdoc>=14.0.0; extra == "dev"
Requires-Dist: pytest>=7.0.0; extra == "dev"
Requires-Dist: pytest-cov>=4.0.0; extra == "dev"
Requires-Dist: pytest-mock>=3.10.0; extra == "dev"
Requires-Dist: mypy>=1.0.0; extra == "dev"
Requires-Dist: toml>=0.10.0; extra == "dev"
Requires-Dist: python-dotenv>=1.0.0; extra == "dev"
Provides-Extra: docs
Requires-Dist: pdoc>=14.0.0; extra == "docs"
Dynamic: license-file
